odoo9_addon_subscription_action-9.0.1.0.0-py2.7-nspkg.pth
odoo9_addon_subscription_action-9.0.1.0.0.dist-info/DESCRIPTION.rst
odoo9_addon_subscription_action-9.0.1.0.0.dist-info/METADATA
odoo9_addon_subscription_action-9.0.1.0.0.dist-info/RECORD
odoo9_addon_subscription_action-9.0.1.0.0.dist-info/WHEEL
odoo9_addon_subscription_action-9.0.1.0.0.dist-info/metadata.json
odoo9_addon_subscription_action-9.0.1.0.0.dist-info/namespace_packages.txt
odoo9_addon_subscription_action-9.0.1.0.0.dist-info/top_level.txt
odoo_addons/subscription_action/README.rst
odoo_addons/subscription_action/__init__.py
odoo_addons/subscription_action/__openerp__.py
odoo_addons/subscription_action/models/__init__.py
odoo_addons/subscription_action/models/subscription_subscription.py
odoo_addons/subscription_action/static/description/icon.png
odoo_addons/subscription_action/tests/__init__.py
odoo_addons/subscription_action/tests/test_subscription_action.py
odoo_addons/subscription_action/views/subscription_subscription.xml
